justopinion/__init__.py
justopinion/citations.py
justopinion/decisions.py
justopinion/download.py
justopinion-0.4.0.dist-info/METADATA
justopinion-0.4.0.dist-info/WHEEL
justopinion-0.4.0.dist-info/top_level.txt
justopinion-0.4.0.dist-info/RECORD
