Metadata-Version: 2.2
Name: justopinion
Version: 0.4.0
Summary: Download client for legal opinions
Home-page: https://github.com/mscarey/justopinion
Author: Matt Carey
Author-email: matt@authorityspoke.com
Project-URL: Bug Tracker, https://github.com/mscarey/justopinion/issues
Classifier: Programming Language :: Python :: 3.11
Classifier: Programming Language :: Python :: 3.12
Classifier: Programming Language :: Python :: 3.13
Classifier: Operating System :: OS Independent
Classifier: License :: Free To Use But Restricted
Classifier: Natural Language :: English
Requires-Python: >=3.11
Requires-Dist: requests~=2.31.0
Requires-Dist: anchorpoint~=0.8.2
Requires-Dist: eyecite~=2.6.3
Requires-Dist: pydantic>=2.4.2
Requires-Dist: python-dotenv
Requires-Dist: python-ranges~=1.2.2
Dynamic: author
Dynamic: author-email
Dynamic: classifier
Dynamic: description
Dynamic: description-content-type
Dynamic: home-page
Dynamic: project-url
Dynamic: requires-dist
Dynamic: requires-python
Dynamic: summary
